TDD/__init__.py
TDD/main.py
T_D_D/__init__.py
T_D_D/main.py
T_D_D-0.0.1.dist-info/METADATA
T_D_D-0.0.1.dist-info/WHEEL
T_D_D-0.0.1.dist-info/entry_points.txt
T_D_D-0.0.1.dist-info/top_level.txt
T_D_D-0.0.1.dist-info/RECORD
